LICENSE
README.md
setup.py
batch_framework/__init__.py
batch_framework/adaptor.py
batch_framework/backend.py
batch_framework/base.py
batch_framework/etl.py
batch_framework/executor.py
batch_framework/parallize.py
batch_framework/rdb.py
batch_framework/storage.py
batch_framework/version.py
batch_framework.egg-info/PKG-INFO
batch_framework.egg-info/SOURCES.txt
batch_framework.egg-info/dependency_links.txt
batch_framework.egg-info/requires.txt
batch_framework.egg-info/top_level.txt
batch_framework/filesystem/__init__.py
batch_framework/filesystem/base.py
batch_framework/filesystem/local.py
batch_framework/filesystem/dropbox/__init__.py
batch_framework/filesystem/dropbox/config.py
batch_framework/filesystem/dropbox/dropbox.py
batch_framework/filesystem/dropbox/util.py