Metadata-Version: 2.1
Name: batch-framework
Version: 0.2.8
Summary: Generate Batch Framework
Home-page: https://github.com/jeffrey82221/batch_framework
Author: jeffreylin
Author-email: jeffrey82221@gmail.com
License: UNKNOWN
Platform: UNKNOWN
Classifier: Programming Language :: Python :: 3
Classifier: License :: OSI Approved :: MIT License
Classifier: Operating System :: OS Independent
Requires-Python: >=3.8, !=3.11.*
License-File: LICENSE
